pyserpent.py
serpent.py
serpent_pyext.so
ethereum_serpent_augur_temp-2.0.2.data/scripts/serpent.py
ethereum_serpent_augur_temp-2.0.2.dist-info/DESCRIPTION.rst
ethereum_serpent_augur_temp-2.0.2.dist-info/METADATA
ethereum_serpent_augur_temp-2.0.2.dist-info/RECORD
ethereum_serpent_augur_temp-2.0.2.dist-info/WHEEL
ethereum_serpent_augur_temp-2.0.2.dist-info/entry_points.txt
ethereum_serpent_augur_temp-2.0.2.dist-info/metadata.json
ethereum_serpent_augur_temp-2.0.2.dist-info/top_level.txt
