Metadata-Version: 2.0
Name: ethereum-serpent-augur-temp
Version: 2.0.2
Summary: Serpent compiler
Home-page: http://www.ethereum.org/
Author: Vitalik Buterin
Author-email: v@buterin.com
License: WTFPL
Platform: UNKNOWN
Classifier: Intended Audience :: Developers
Classifier: Programming Language :: Python :: 2
Classifier: Programming Language :: Python :: 2.7
Classifier: Programming Language :: Python :: 3
Classifier: Programming Language :: Python :: 3.4
Classifier: Programming Language :: Python :: 3.5
